{
  "_partial": true,
  "_source": "ocr",
  "cds_code": "19-73445",
  "compliance": {
    "ocr_open_investigations": {
      "as_of": "2025-01-14",
      "fetched_at": "2026-05-23T03:10:47Z",
      "note": "Disability - FAPE (opened 01/10/2025); Title VI - English Language Learners (opened 01/04/2024)",
      "source": "ocr",
      "url": "https://ocrcas.ed.gov/open-investigations",
      "value": 2
    },
    "ocr_open_investigations_disability": {
      "as_of": "2025-01-14",
      "fetched_at": "2026-05-23T03:10:47Z",
      "source": "ocr",
      "url": "https://ocrcas.ed.gov/open-investigations",
      "value": 1
    }
  }
}