{
  "_partial": true,
  "_source": "ocr",
  "cds_code": "37-68056",
  "compliance": {
    "ocr_open_investigations": {
      "as_of": "2025-01-14",
      "fetched_at": "2026-05-23T03:10:47Z",
      "note": "Disability - FAPE (opened 05/02/2024); Disability - Restraint and Seclusion (opened 05/02/2024); Title IX - Denial of Benefits (opened 05/02/2024)",
      "source": "ocr",
      "url": "https://ocrcas.ed.gov/open-investigations",
      "value": 3
    },
    "ocr_open_investigations_disability": {
      "as_of": "2025-01-14",
      "fetched_at": "2026-05-23T03:10:47Z",
      "source": "ocr",
      "url": "https://ocrcas.ed.gov/open-investigations",
      "value": 2
    }
  }
}