{
  "_academic_year": "2024-25",
  "_partial": true,
  "_source": "ca_dashboard",
  "cds_code": "19-64535",
  "outcome_metrics": {
    "chronic_absenteeism_rate_all": {
      "as_of": "2025-06-30",
      "fetched_at": "2026-05-23T03:10:42Z",
      "source": "ca_dashboard",
      "url": "https://www.cde.ca.gov/ta/ac/cm/dashboardresources.asp",
      "value": 0.061
    },
    "chronic_absenteeism_rate_swd": {
      "as_of": "2025-06-30",
      "fetched_at": "2026-05-23T03:10:42Z",
      "source": "ca_dashboard",
      "url": "https://www.cde.ca.gov/ta/ac/cm/dashboardresources.asp",
      "value": 0.139
    },
    "ela_distance_from_standard_all": {
      "as_of": "2025-06-30",
      "fetched_at": "2026-05-23T03:10:42Z",
      "source": "ca_dashboard",
      "url": "https://www.cde.ca.gov/ta/ac/cm/dashboardresources.asp",
      "value": 65.1
    },
    "ela_distance_from_standard_swd": {
      "as_of": "2025-06-30",
      "fetched_at": "2026-05-23T03:10:42Z",
      "source": "ca_dashboard",
      "url": "https://www.cde.ca.gov/ta/ac/cm/dashboardresources.asp",
      "value": -36.9
    },
    "math_distance_from_standard_all": {
      "as_of": "2025-06-30",
      "fetched_at": "2026-05-23T03:10:42Z",
      "source": "ca_dashboard",
      "url": "https://www.cde.ca.gov/ta/ac/cm/dashboardresources.asp",
      "value": 50.1
    },
    "math_distance_from_standard_swd": {
      "as_of": "2025-06-30",
      "fetched_at": "2026-05-23T03:10:42Z",
      "source": "ca_dashboard",
      "url": "https://www.cde.ca.gov/ta/ac/cm/dashboardresources.asp",
      "value": -68.1
    },
    "suspension_rate_all": {
      "as_of": "2025-06-30",
      "fetched_at": "2026-05-23T03:10:42Z",
      "source": "ca_dashboard",
      "url": "https://www.cde.ca.gov/ta/ac/cm/dashboardresources.asp",
      "value": 0.01
    },
    "suspension_rate_swd": {
      "as_of": "2025-06-30",
      "fetched_at": "2026-05-23T03:10:42Z",
      "source": "ca_dashboard",
      "url": "https://www.cde.ca.gov/ta/ac/cm/dashboardresources.asp",
      "value": 0.026
    }
  }
}